sopel_unicode/__init__.py
sopel_unicode/impl.py
sopel_unicode/plugin.py
sopel_unicode-1.0.0.dist-info/licenses/COPYING
sopel_unicode-1.0.0.dist-info/METADATA
sopel_unicode-1.0.0.dist-info/WHEEL
sopel_unicode-1.0.0.dist-info/entry_points.txt
sopel_unicode-1.0.0.dist-info/top_level.txt
sopel_unicode-1.0.0.dist-info/RECORD
