Metadata-Version: 2.4
Name: sopel-unicode
Version: 1.0.0
Summary: Unicode information lookup plugin for Sopel
Author: SnoopJ
License-Expression: EFL-2.0
Project-URL: Homepage, https://github.com/sopel-irc/sopel-unicode
Project-URL: Bug Tracker, https://github.com/sopel-irc/sopel-unicode/issues
Keywords: sopel,plugin,bot,irc
Classifier: Intended Audience :: Developers
Classifier: Intended Audience :: System Administrators
Classifier: Topic :: Communications :: Chat :: Internet Relay Chat
Classifier: Programming Language :: Python :: 3.8
Classifier: Programming Language :: Python :: 3.9
Classifier: Programming Language :: Python :: 3.10
Classifier: Programming Language :: Python :: 3.11
Classifier: Programming Language :: Python :: 3.12
Classifier: Programming Language :: Python :: 3.13
Requires-Python: <4,>=3.8
License-File: COPYING
Requires-Dist: sopel>=8.0
Provides-Extra: ucd
Requires-Dist: unicodedata2; extra == "ucd"
Provides-Extra: age
Requires-Dist: unicode_age; extra == "age"
Provides-Extra: all
Requires-Dist: sopel-unicode[UCD]; extra == "all"
Requires-Dist: sopel-unicode[age]; extra == "all"
Dynamic: license-file
